mmkfeatures/__init__.py
mmkfeatures/fusion/__init__.py
mmkfeatures/fusion/blank.py
mmkfeatures/fusion/computational_sequence.py
mmkfeatures/fusion/computational_sequence_x.py
mmkfeatures/fusion/dataset.py
mmkfeatures/fusion/download_ops.py
mmkfeatures/fusion/file_ops.py
mmkfeatures/fusion/integrity_check.py
mmkfeatures/fusion/log.py
mmkfeatures/fusion/metadataconfigs.py
mmkfeatures/fusion/mm_features_lib.py
mmkfeatures/fusion/mm_features_node.py
mmkfeatures/fusion/read_mosi_h5_file.py
mmkfeatures/fusion/LSTHM/LSTHM.py
mmkfeatures/fusion/LSTHM/__init__.py
mmkfeatures/fusion/LSTHM/test.py
mmkfeatures/fusion/dynamic_fusion_graph/__init__.py
mmkfeatures/fusion/dynamic_fusion_graph/model.py
mmkfeatures/fusion/multiple_attention/__init__.py
mmkfeatures/fusion/multiple_attention/model.py
mmkfeatures/fusion/recurrent_fusion/__init__.py
mmkfeatures/fusion/recurrent_fusion/model.py
mmkfeatures/fusion/tensor_fusion/__init__.py
mmkfeatures/fusion/tensor_fusion/model.py
mmkfeatures/graph/__init__.py
mmkfeatures/graph/cgan_node.py
mmkfeatures/graph/cnn_node.py
mmkfeatures/graph/gan_node.py
mmkfeatures/image/__init__.py
mmkfeatures/image/bow_extractor.py
mmkfeatures/image/clutering_model.py
mmkfeatures/image/color_descriptor.py
mmkfeatures/image/conv_autoencoder.py
mmkfeatures/image/deep_extractor.py
mmkfeatures/image/extractor.py
mmkfeatures/image/image_autoencocer_builder.py
mmkfeatures/image/image_features_wrapper.py
mmkfeatures/image/image_model.py
mmkfeatures/image/image_processing.py
mmkfeatures/image/image_searcher.py
mmkfeatures/image/lbp_extractor.py
mmkfeatures/index/__init__.py
mmkfeatures/index/index_inverted_op.py
mmkfeatures/index/index_positional_op.py
mmkfeatures/models/__init__.py
mmkfeatures/models/image_text_fusion/__init__.py
mmkfeatures/models/image_text_fusion/image_text_feature_wrapper.py
mmkfeatures/models/image_text_fusion/result_analysis.py
mmkfeatures/models/image_text_fusion/char_embedding/__init__.py
mmkit_features-0.0.1a4.dist-info/LICENSE
mmkit_features-0.0.1a4.dist-info/METADATA
mmkit_features-0.0.1a4.dist-info/WHEEL
mmkit_features-0.0.1a4.dist-info/top_level.txt
mmkit_features-0.0.1a4.dist-info/RECORD
