Metadata-Version: 2.1
Name: mmkit-features
Version: 0.0.1a4
Summary: A multimodal architecture to build multimodal knowledge graphs with flexible multimodal feature extraction and dynamic multimodal concept generation.
Home-page: https://github.com/dhchenx/mmkit-features
Author: Donghua Chen
Author-email: douglaschan@126.com
License: MIT
Project-URL: Bug Reports, https://github.com/dhchenx/mmkit-features/issues
Project-URL: Source, https://github.com/dhchenx/mmkit-features
Keywords: multimodal features,multimodal data,knowledge base
Platform: UNKNOWN
Classifier: Development Status :: 3 - Alpha
Classifier: Intended Audience :: Developers
Classifier: Topic :: Software Development :: Build Tools
Classifier: License :: OSI Approved :: MIT License
Classifier: Programming Language :: Python :: 3
Classifier: Programming Language :: Python :: 3.6
Classifier: Programming Language :: Python :: 3.7
Classifier: Programming Language :: Python :: 3.8
Classifier: Programming Language :: Python :: 3.9
Classifier: Programming Language :: Python :: 3 :: Only
Requires-Python: >=3.6, <4
Requires-Dist: numpy
Requires-Dist: validators
Requires-Dist: tqdm
Requires-Dist: requests
Requires-Dist: h5py
Requires-Dist: nexusformat
Requires-Dist: torch (>=1.9.1)
Requires-Dist: opencv-python
Requires-Dist: librosa (>=0.9.1)
Requires-Dist: sklearn
Requires-Dist: spacy (>=3.2.3)
Requires-Dist: torchvision
Requires-Dist: ffmpeg-python
Requires-Dist: tensorflow (>=2.8)
Requires-Dist: transformers (>=4.29.0)
Requires-Dist: matplotlib
Requires-Dist: timm
Requires-Dist: scipy (>=1.8.0)
Requires-Dist: pandas
Requires-Dist: keras (>=2.6.0)
Requires-Dist: imageio (>=2.19.0)
Requires-Dist: pillow (>=9.0.1)
Requires-Dist: imutils (>=0.5.4)
Provides-Extra: dev
Requires-Dist: check-manifest ; extra == 'dev'
Provides-Extra: test
Requires-Dist: coverage ; extra == 'test'
